youtube_crud/__init__.py
youtube_crud/youtube_client.py
youtube_crud-0.1.0.dist-info/METADATA
youtube_crud-0.1.0.dist-info/WHEEL
youtube_crud-0.1.0.dist-info/RECORD
